{
  "main": {
    "id": "db99fe36cfd95b53",
    "type": "split",
    "children": [
      {
        "id": "ea387e39b4b4b302",
        "type": "tabs",
        "children": [
          {
            "id": "2d9a83d935a87f02",
            "type": "leaf",
            "state": {
              "type": "pdf",
              "state": {
                "file": "CollectionPDF/Asuka & Shinji's Infinite Playlist(1-21).pdf"
              }
            }
          },
          {
            "id": "b288be7365691009",
            "type": "leaf",
            "state": {
              "type": "markdown",
              "state": {
                "file": "RLLRRR - ❤️Asuka&Shinji's Infinite Playlist.md",
                "mode": "source",
                "source": false
              }
            }
          },
          {
            "id": "bb4265ac9c5646d3",
            "type": "leaf",
            "state": {
              "type": "pdf",
              "state": {
                "file": "CollectionPDF/You Are (Not) at Fault 你（没）有错 全文翻译.pdf"
              }
            }
          },
          {
            "id": "a62972abd882eb61",
            "type": "leaf",
            "state": {
              "type": "markdown",
              "state": {
                "file": "m3m3nt0v1v3r3 - Dreams of a Distant.md",
                "mode": "source",
                "source": false
              }
            }
          },
          {
            "id": "7b747532fba47aa3",
            "type": "leaf",
            "state": {
              "type": "markdown",
              "state": {
                "file": "Eric Blair - 30 Kisses, 30 Ways Asuka and Shinji.md",
                "mode": "source",
                "source": false
              }
            }
          },
          {
            "id": "178bfddd18641a4a",
            "type": "leaf",
            "state": {
              "type": "markdown",
              "state": {
                "file": "Donderkind - Neon Genesis Evangelion：Propinquity.md",
                "mode": "source",
                "source": false
              }
            }
          },
          {
            "id": "0df9433e9955cad0",
            "type": "leaf",
            "state": {
              "type": "markdown",
              "state": {
                "file": "Karina Kineshi - To My Dearest Honey.md",
                "mode": "source",
                "source": false
              }
            }
          },
          {
            "id": "ff9c95caf0c1a28d",
            "type": "leaf",
            "state": {
              "type": "markdown",
              "state": {
                "file": "Red Horseman - Pheonix Rising.md",
                "mode": "source",
                "source": false
              }
            }
          },
          {
            "id": "ee212f634c309768",
            "type": "leaf",
            "state": {
              "type": "pdf",
              "state": {
                "file": "CollectionPDF/新生 The 2nd try.pdf"
              }
            }
          },
          {
            "id": "f162476866302f84",
            "type": "leaf",
            "state": {
              "type": "markdown",
              "state": {
                "file": "AngelNo13Bardiel - Go back to sleep, precious.md",
                "mode": "source",
                "source": false
              }
            }
          },
          {
            "id": "f318132a79a6492e",
            "type": "leaf",
            "state": {
              "type": "markdown",
              "state": {
                "file": "AngelNo13Bardiel - Let Me See You Stripped, Down to the Bone.md",
                "mode": "source",
                "source": false
              }
            }
          },
          {
            "id": "9ebd71afd21f8115",
            "type": "leaf",
            "state": {
              "type": "markdown",
              "state": {
                "file": "AngelNo13Bardiel - Let Me See You Stripped, Down to the Bone.md",
                "mode": "source",
                "source": false
              }
            }
          },
          {
            "id": "267d144a05858a46",
            "type": "leaf",
            "state": {
              "type": "markdown",
              "state": {
                "file": "SerialRavist - Orchestating the Silence.md",
                "mode": "source",
                "source": false
              }
            }
          }
        ],
        "currentTab": 12
      }
    ],
    "direction": "vertical"
  },
  "left": {
    "id": "a2a774d0e6fe3da4",
    "type": "split",
    "children": [
      {
        "id": "605d3e0516f958ad",
        "type": "tabs",
        "children": [
          {
            "id": "cae18b189083064c",
            "type": "leaf",
            "state": {
              "type": "file-explorer",
              "state": {
                "sortOrder": "alphabetical"
              }
            }
          },
          {
            "id": "54f9059b165e295c",
            "type": "leaf",
            "state": {
              "type": "bookmarks",
              "state": {}
            }
          },
          {
            "id": "2f4432c7012e8683",
            "type": "leaf",
            "state": {
              "type": "search",
              "state": {
                "query": "file:a glass of wine",
                "matchingCase": false,
                "explainSearch": true,
                "collapseAll": true,
                "extraContext": true,
                "sortOrder": "alphabetical"
              }
            }
          }
        ]
      }
    ],
    "direction": "horizontal",
    "width": 300
  },
  "right": {
    "id": "782b2139fefb92cb",
    "type": "split",
    "children": [
      {
        "id": "3703cdda1cbf3392",
        "type": "tabs",
        "children": [
          {
            "id": "2dad7f8635942b5a",
            "type": "leaf",
            "state": {
              "type": "backlink",
              "state": {
                "file": "SerialRavist - Orchestating the Silence.md",
                "collapseAll": false,
                "extraContext": false,
                "sortOrder": "alphabetical",
                "showSearch": false,
                "searchQuery": "",
                "backlinkCollapsed": false,
                "unlinkedCollapsed": true
              }
            }
          },
          {
            "id": "f6aee78ff37308f1",
            "type": "leaf",
            "state": {
              "type": "outgoing-link",
              "state": {
                "file": "SerialRavist - Orchestating the Silence.md",
                "linksCollapsed": false,
                "unlinkedCollapsed": true
              }
            }
          },
          {
            "id": "55c4da4a4527ada0",
            "type": "leaf",
            "state": {
              "type": "tag",
              "state": {
                "sortOrder": "frequency",
                "useHierarchy": true
              }
            }
          },
          {
            "id": "c45078173a650ebd",
            "type": "leaf",
            "state": {
              "type": "outline",
              "state": {
                "file": "SerialRavist - Orchestating the Silence.md"
              }
            }
          }
        ]
      }
    ],
    "direction": "horizontal",
    "width": 300,
    "collapsed": true
  },
  "left-ribbon": {
    "hiddenItems": {
      "switcher:打开快速切换": false,
      "graph:查看关系图谱": false,
      "canvas:新建白板": false,
      "templates:插入模板": false,
      "command-palette:打开命令面板": false,
      "workspaces:管理工作区布局": false
    }
  },
  "active": "267d144a05858a46",
  "lastOpenFiles": [
    "AngelNo13Bardiel - Let Me See You Stripped, Down to the Bone.md",
    "SerialRavist - Orchestating the Silence.md",
    "AngelNo13Bardiel - Go back to sleep, precious.md",
    "AngelNo13B - Sing this corrosion to me.md",
    "CollectionPDF/AngelNo13Bardiel三部曲.pdf",
    "CollectionPDF/新生 The 2nd try.pdf",
    "CollectionPDF/漫长的告白（新世纪福音战士嗣香同人合集）.pdf",
    "Toasterman、94Saturn - A Glass of Wine.md",
    "Axel Terizaki - Asuka, Will You Dance With Me？.md",
    "CollectionPDF/A Glass of Wine.pdf",
    "CollectionPDF/[翻译]Asuka, Will You Dance With Me.pdf",
    "Axel Terizaki - Shinji, will you dance with me？.md",
    "atare - Asushin Winter Contest - Crunching Snow.md",
    "Aki-Chan04 - ❤️Das Ewige Dasein (The Eternal Life).md",
    "AgentKaji - The Second Impact.md",
    "AgentKaji - A Recipe for Trouble.md",
    "AgentKaji - ❤️The Asuka Variations.md",
    "CollectionPDF/[翻译]Shinji, Will You Dance With Me.pdf",
    "JimmyWolk - The Second Try.md",
    "CollectionPDF/Shinji, Will You Dance With Me.pdf",
    "CollectionPDF/Asuka, Will You Dance With Me.pdf",
    "CollectionPDF/~$INJI,WILL YOU DANCE WITH ME（翻译） 1.docx",
    "CollectionPDF/~$UKA, WILL YOU DANCE WITH ME（翻译） 1.docx",
    "Axel Terizaki -.md",
    "JimmyWolk -.md",
    "Random1377 - Sanshuunoomoi.md",
    "TalonEmpire - You Can (Not) Redo.md",
    "Red Horseman - Pheonix Rising.md",
    "Karina Kineshi - To My Dearest Honey.md",
    "Donderkind - Unbroken.md",
    "Donderkind - Neon Genesis Evangelion：Propinquity.md",
    "Eric Blair - 30 Kisses, 30 Ways Asuka and Shinji.md",
    "m3m3nt0v1v3r3 - Dreams of a Distant.md",
    "MisterHalt - You Are (Not) At Fault.md",
    "RLLRRR - ❤️Asuka&Shinji's Infinite Playlist.md",
    "MisterHalt - ❤️Read The Fine Print.md"
  ]
}